README.rst
setup.cfg
setup.py
pyyasm/__init__.py
pyyasm/exception.py
pyyasm.egg-info/PKG-INFO
pyyasm.egg-info/SOURCES.txt
pyyasm.egg-info/dependency_links.txt
pyyasm.egg-info/top_level.txt
pyyasm/ressources/__init__.py
pyyasm/ressources/yasm_32bit.exe
pyyasm/ressources/yasm_64bit.exe
tests/__init__.py
tests/test_pyyasm.py