Metadata-Version: 1.1
Name: pyyasm
Version: 0.0.1
Summary: A python Yasm Wrapper for x86 and x64.
Home-page: https://github.com/srounet/pyyasm
Author: Fabien Reboia
Author-email: srounet@gmail.com
License: BSD
Download-URL: https://github.com/srounet/pyyasm/archive/0.0.1.tar.gz
Platform: UNKNOWN
Classifier: Programming Language :: Python :: 3.4
Classifier: Programming Language :: Assembly
Classifier: Environment :: Win32 (MS Windows)
Classifier: Intended Audience :: Developers
Classifier: License :: OSI Approved :: BSD License
